raylibpy/__init__.py
raylibpy/easings.py
raylibpy/bin/32bit/libraylib.5.0.0.dylib
raylibpy/bin/32bit/raylib.dll
raylibpy/bin/32bit/testlib.dll
raylibpy/bin/64bit/libraylib.5.0.0.dylib
raylibpy/bin/64bit/libraylib.so.5.0.0
raylibpy/bin/64bit/raylib.dll
raylibpy/bin/64bit/testlib.dll
raylib_py-5.5.0.dist-info/LICENSE
raylib_py-5.5.0.dist-info/METADATA
raylib_py-5.5.0.dist-info/WHEEL
raylib_py-5.5.0.dist-info/top_level.txt
raylib_py-5.5.0.dist-info/RECORD
