Metadata-Version: 2.1
Name: raylib-py
Version: 5.5.0
Summary: A simple and easy-to-use library to enjoy videogames programming (written in C, wrapped with ctypes)
Author-email: "Jorge A. Gomes" <jorgegomes83@protonmail.com>
Project-URL: Homepage, https://github.com/overdev/raylibpyctbg
Project-URL: Bug Tracker, https://github.com/overdev/raylibpyctbg/issues
Classifier: Programming Language :: Python :: 3
Classifier: License :: OSI Approved :: MIT License
Classifier: Operating System :: OS Independent
Requires-Python: >=3.3
License-File: LICENSE
